requests_utils/__init__.py
requests_utils/api_with_tools.py
requests_utils/api_with_tools.pyi
requests_utils/avoid_sslerror.py
requests_utils/broadcast_list.py
requests_utils/broadcast_list.pyi
requests_utils/contants.py
requests_utils/custom_defaults.py
requests_utils/custom_defaults.pyi
requests_utils/dealing_unhashable_args.py
requests_utils/exceptions.py
requests_utils/header_utils.py
requests_utils/requests_.py
requests_utils/response_proxy.py
requests_utils/sessions_with_tools.py
requests_utils/sessions_with_tools.pyi
requests_utils/souptools.py
requests_utils/souptoolsclass.py
requests_utils-0.4.1.dist-info/LICENSE
requests_utils-0.4.1.dist-info/METADATA
requests_utils-0.4.1.dist-info/WHEEL
requests_utils-0.4.1.dist-info/top_level.txt
requests_utils-0.4.1.dist-info/RECORD
