Metadata-Version: 2.1
Name: requests-utils
Version: 0.4.1
Summary: Various convenient features about requests.
Home-page: https://github.com/ilotoki0804/requests-utils
Author: ilotoki0804
Author-email: ilotoki0804@gmail.com
License: MIT
Keywords: requests,bs4,BeautifulSoup,async,caching,cache
Classifier: License :: OSI Approved :: MIT License
Classifier: Operating System :: OS Independent
Classifier: Programming Language :: Python :: 3.10
Classifier: Programming Language :: Python :: 3.11
Classifier: Framework :: AsyncIO
Classifier: Environment :: Web Environment
Classifier: Intended Audience :: Developers
Classifier: Topic :: Internet :: WWW/HTTP
Requires-Python: >=3.10
License-File: LICENSE
Requires-Dist: requests
Requires-Dist: beautifulsoup4
Requires-Dist: frozendict
Requires-Dist: typing-extensions
